discopat/__init__.py
discopat/basics.py
discopat/display.py
discopat/tokam.py
discopat/tracking.py
discopat/utils.py
discopat/cdl/__init__.py
discopat/cdl/rosecdl.py
discopat/core/__init__.py
discopat/core/value_objects.py
discopat/core/entities/__init__.py
discopat/core/entities/annotation.py
discopat/core/entities/array.py
discopat/core/entities/data.py
discopat/core/entities/detection.py
discopat/core/entities/frame.py
discopat/core/entities/metadata.py
discopat/core/entities/movie.py
discopat/core/entities/tracking.py
discopat/datasets/__init__.py
discopat/datasets/torch.py
discopat/manual_annotations/__init__.py
discopat/manual_annotations/operations.py
discopat/manual_annotations/yolo.py
discopat/manual_annotations/cvat/__init__.py
discopat/manual_annotations/cvat/import.py
discopat/manual_annotations/cvat/prepare.py
discopat/metrics/__init__.py
discopat/nn_models/__init__.py
discopat/nn_models/faster_rcnn.py
discopat/nn_training/__init__.py
discopat/nn_training/nn_trainer.py
discopat/nn_training/torch.py
discopat/nn_training/utils.py
discopat/nn_training/evaluation/__init__.py
discopat/nn_training/evaluation/base.py
discopat/nn_training/evaluation/matching.py
discopat/nn_training/torch_detection_utils/__init__.py
discopat/nn_training/torch_detection_utils/coco_eval.py
discopat/nn_training/torch_detection_utils/coco_utils.py
discopat/nn_training/torch_detection_utils/engine.py
discopat/nn_training/torch_detection_utils/transforms.py
discopat/nn_training/torch_detection_utils/utils.py
discopat/projects/tokam/__init__.py
discopat/repositories/__init__.py
discopat/repositories/factory.py
discopat/repositories/hdf5.py
discopat/repositories/local.py
discopat/repositories/mot.py
discopat/repositories/osf.py
discopat/repositories/png.py
discopat/repositories/repository.py
discopat-0.4.3.dist-info/licenses/LICENSE
discopat-0.4.3.dist-info/METADATA
discopat-0.4.3.dist-info/WHEEL
discopat-0.4.3.dist-info/top_level.txt
discopat-0.4.3.dist-info/RECORD
