Metadata-Version: 2.4
Name: discopat
Version: 0.4.3
Summary: DISCOver PATterns (DISCOPAT)
Author-email: Mansour Benbakoura <mansour.benbakoura@inria.fr>
License: BSD 3-Clause License
Project-URL: Repository, https://github.com/mansour-b/discopat
Project-URL: Documentation, https://discopat.readthedocs.io
Classifier: Intended Audience :: Science/Research
Classifier: Operating System :: OS Independent
Classifier: Programming Language :: Python :: 3
Classifier: Programming Language :: Python :: 3.9
Classifier: Programming Language :: Python :: 3.10
Classifier: Programming Language :: Python :: 3.11
Classifier: Programming Language :: Python :: 3.12
Classifier: Programming Language :: Python :: 3.13
Classifier: Programming Language :: Python :: 3.14
Requires-Python: >=3.9
License-File: LICENSE
Requires-Dist: filterpy
Requires-Dist: h5py
Requires-Dist: imageio
Requires-Dist: ipykernel
Requires-Dist: matplotlib
Requires-Dist: numpy
Requires-Dist: osfclient
Requires-Dist: pycocotools
Requires-Dist: PyYAML
Requires-Dist: scikit-image
Requires-Dist: torch
Requires-Dist: torchaudio
Requires-Dist: torchvision
Requires-Dist: tqdm
Provides-Extra: dev
Requires-Dist: ruff; extra == "dev"
Provides-Extra: doc
Requires-Dist: sphinx; extra == "doc"
Requires-Dist: sphinx-gallery; extra == "doc"
Requires-Dist: sphinx_rtd_theme; extra == "doc"
Provides-Extra: test
Requires-Dist: pytest; extra == "test"
Requires-Dist: pytest-cov; extra == "test"
Dynamic: license-file
